pedalparser/__init__.py
pedalparser/bodybike/__init__.py
pedalparser/bodybike/models.py
pedalparser/bodybike/parser.py
pedalparser/py.typed
pedalparser-0.1.0.dist-info/licenses/LICENSE.md
pedalparser-0.1.0.dist-info/WHEEL
pedalparser-0.1.0.dist-info/METADATA
pedalparser-0.1.0.dist-info/RECORD
