Metadata-Version: 2.4
Name: pedalparser
Version: 0.1.0
Summary: Parse and analyze workout data exported from stationary bikes
Keywords: cycling,workout,fitness,bodybike,exercise
Author: Vegard Egeland
Author-email: Vegard Egeland <vegardegeland@gmail.com>
License-Expression: MIT
License-File: LICENSE.md
Classifier: Development Status :: 4 - Beta
Classifier: Intended Audience :: Developers
Classifier: Intended Audience :: Science/Research
Classifier: License :: OSI Approved :: MIT License
Classifier: Operating System :: OS Independent
Classifier: Programming Language :: Python :: 3
Classifier: Programming Language :: Python :: 3.11
Classifier: Programming Language :: Python :: 3.12
Classifier: Programming Language :: Python :: 3.13
Classifier: Programming Language :: Python :: 3.14
Classifier: Topic :: Scientific/Engineering :: Information Analysis
Classifier: Typing :: Typed
Requires-Dist: numpy>=1.24
Requires-Dist: pandas ; extra == 'pandas'
Requires-Dist: polars ; extra == 'polars'
Requires-Python: >=3.11
Project-URL: Changelog, https://github.com/vegardege/pedalparser/blob/master/CHANGELOG.md
Project-URL: Documentation, https://github.com/vegardege/pedalparser
Project-URL: Issues, https://github.com/vegardege/pedalparser/issues
Project-URL: Repository, https://github.com/vegardege/pedalparser
Provides-Extra: pandas
Provides-Extra: polars
